loyalcat/types/endpoints.py
loyalcat-0.0.1.dist-info/METADATA
loyalcat-0.0.1.dist-info/WHEEL
loyalcat-0.0.1.dist-info/entry_points.txt
loyalcat-0.0.1.dist-info/top_level.txt
loyalcat-0.0.1.dist-info/RECORD
